[
  {
    "id": 1,
    "title": "Уважение к старшим",
    "text": "В знак глубокого уважения и внимания к людям старшего поколения мы запускаем бессрочную акцию.&nbsp; На любую услугу.",
    "img": "/uploads/2025/08/slide1_1755518302018_fd1416e8d045.png",
    "discount": "-20%",
    "price": {
      "old": "",
      "new": "",
      "label": ""
    },
    "ctaText": "Посмотреть все акции",
    "ctaHref": "/akcii",
    "free": false,
    "offers": [
      {
        "id": "7lsiefkdo5wmeqv1g9j",
        "text": "",
        "free": false,
        "price": {
          "old": "",
          "new": "",
          "label": ""
        }
      }
    ]
  },
  {
    "id": 2,
    "title": "Цельноциркониевая коронка на свой зуб под ключ",
    "text": "Мы запускаем сезон акций на обследование и диагностику челюстно-лицевой области!",
    "img": "/uploads/2025/08/slide4_1755804054010_ec9f9ad950e1.png",
    "discount": "",
    "price": {
      "old": "33300",
      "new": "37000",
      "label": ""
    },
    "ctaText": "",
    "ctaHref": "",
    "free": false,
    "offers": [
      {
        "id": "8nmwppbqc1lmeqvfav9",
        "text": "Комплексное обследование челюстно-лицевой:",
        "free": false,
        "price": {
          "old": 33300,
          "new": 37000,
          "label": ""
        }
      },
      {
        "id": "ma1082tpquemeqvig1m",
        "text": "Консультанция и план лечения",
        "free": true,
        "price": null
      }
    ]
  },
  {
    "id": 3,
    "title": "Комплексное обследование челюстно-лицевой области",
    "text": "<br>",
    "img": "/uploads/2025/08/slide3_1755804030842_fc3fb033842b.png",
    "discount": "",
    "price": {
      "old": "5000",
      "new": "3000",
      "label": "Бесплатно "
    },
    "ctaText": "",
    "ctaHref": "",
    "free": false,
    "offers": [
      {
        "id": "ekqz9eoxvfimeqv25ws",
        "text": "Мы запускаем сезон акций! Только с 25.09.23 по 31.10.23 комплексное обследование челюстно-лицевой области (снимок КТ) за",
        "free": false,
        "price": {
          "old": 3000,
          "new": 5000,
          "label": ""
        }
      },
      {
        "id": "tnpk0iwy2mdmeqvlece",
        "text": "Консультаци и план лечения&nbsp;",
        "free": true,
        "price": null
      }
    ]
  },
  {
    "id": 4,
    "title": "Гигиена полости рта",
    "text": "<br>",
    "img": "/uploads/2025/08/slide2_1755804155402_4ffde7ad4e41.png",
    "discount": "",
    "price": {
      "old": "",
      "new": "",
      "label": ""
    },
    "ctaText": "",
    "ctaHref": "",
    "free": false,
    "offers": [
      {
        "id": "1tgtqu2skbhmeqvheqf",
        "text": "Уникальная возможность выполнить гигиену полости рта (ультразвуковая обработка, порошок Air-Flow, полировка специальной пастой, покрытие фтор лаком, рекомендации по уходу за зубами)",
        "free": false,
        "price": {
          "old": 6900,
          "new": 4900,
          "label": ""
        }
      }
    ]
  }
]